CoMBCR/CoMBCR.py
CoMBCR/__init__.py
CoMBCR/utils.py
CoMBCR/tokenizer/__init__.py
CoMBCR/tokenizer/merges.txt
CoMBCR/tokenizer/vocab.json
CoMBCR-0.1.4.dist-info/LICENSE.md
CoMBCR-0.1.4.dist-info/METADATA
CoMBCR-0.1.4.dist-info/WHEEL
CoMBCR-0.1.4.dist-info/top_level.txt
CoMBCR-0.1.4.dist-info/RECORD
