Metadata-Version: 2.1
Name: CoMBCR
Version: 0.1.4
Summary: A python lib for CoMBCR
Home-page: https://github.com/deepomicslab/CoMBCR.git/
Author: Yiping Zou
Author-email: yipingzou2-c@my.cityu.edu.hk
License: MIT
Classifier: Programming Language :: Python :: 3
Classifier: License :: OSI Approved :: MIT License
Classifier: Operating System :: OS Independent
Requires-Python: >=3.6
License-File: LICENSE.md
